CHANGELOG.txt
LICENSE.txt
MANIFEST.in
README.txt
code.py
env.yml
setup.py
.pytest_cache/README.md
datasets/housing/housing.csv
datasets/housing/housing.tgz
datasets/housing/housing_prepared.csv
datasets/housing/testing_prepared.csv
docs/build/html/_sources/code_installation.rst.txt
docs/build/html/_sources/index.rst.txt
docs/build/html/_sources/predict.rst.txt
docs/build/html/_sources/score_pretrained.rst.txt
docs/build/html/_sources/train_model.rst.txt
docs/source/conf.py
gloria_housing.egg-info/PKG-INFO
gloria_housing.egg-info/SOURCES.txt
gloria_housing.egg-info/dependency_links.txt
gloria_housing.egg-info/top_level.txt
glowriya_housing.egg-info/SOURCES.txt
glowriya_housing.egg-info/dependency_links.txt
glowriya_housing.egg-info/top_level.txt
src/gloria_housing/__init__.py
src/gloria_housing/nonstandardcode.py
src/gloria_housing/predict.log
src/gloria_housing/predict.py
src/gloria_housing/score_pretrained.log
src/gloria_housing/score_pretrained.py
src/gloria_housing/train_datasets.py
src/gloria_housing/train_score_model.log
src/gloria_housing/train_score_model.py
tests_housing/funtions.py
tests_housing/test_dtype_pytest.py
tests_housing/test_dtype_unittest.py
tests_housing/test_housing_pytest.py
tests_housing/test_housing_unittest.py
tests_housing/var_dtype.py